etekcity_esf551_ble/__init__.py
etekcity_esf551_ble/_version.py
etekcity_esf551_ble/body_metrics.py
etekcity_esf551_ble/const.py
etekcity_esf551_ble/parser.py
etekcity_esf551_ble-0.3.12.dist-info/METADATA
etekcity_esf551_ble-0.3.12.dist-info/WHEEL
etekcity_esf551_ble-0.3.12.dist-info/licenses/LICENSE
etekcity_esf551_ble-0.3.12.dist-info/RECORD
