Metadata-Version: 2.4
Name: etekcity_esf551_ble
Version: 0.3.12
Summary: An unofficial Python package for interacting with Etekcity ESF-551 Smart Fitness Scales using BLE. Not affiliated with Etekcity, VeSync Co., Ltd., or any of their subsidiaries.
Project-URL: Homepage, https://github.com/ronnnnnnnnnnnnn/etekcity_esf551_ble
Project-URL: Bug Tracker, https://github.com/ronnnnnnnnnnnnn/etekcity_esf551_ble/issues
Project-URL: Documentation, https://github.com/ronnnnnnnnnnnnn/etekcity_esf551_ble#readme
Project-URL: Source Code, https://github.com/ronnnnnnnnnnnnn/etekcity_esf551_ble
Author-email: Ron <ronnnnnnn@gmail.com>
License-Expression: MIT
License-File: LICENSE
Keywords: ble,bluetooth,esf551,etekcity,fitness scale,health,iot,smart home,smart scale,weight
Classifier: Intended Audience :: Developers
Classifier: License :: OSI Approved :: MIT License
Classifier: Operating System :: OS Independent
Classifier: Programming Language :: Python :: 3
Classifier: Programming Language :: Python :: 3.11
Classifier: Programming Language :: Python :: 3.12
Classifier: Programming Language :: Python :: 3.13
Classifier: Topic :: Home Automation
Classifier: Topic :: Software Development :: Libraries :: Python Modules
Requires-Python: >=3.10
Requires-Dist: bleak-retry-connector
Requires-Dist: bleak>=2.0.0
